stellar_core_prometheus_exporter/__init__.py
stellar_core_prometheus_exporter/exporter.py
stellar_core_prometheus_exporter/lib.py
stellar_core_prometheus_exporter-0.10.6.dist-info/LICENSE
stellar_core_prometheus_exporter-0.10.6.dist-info/METADATA
stellar_core_prometheus_exporter-0.10.6.dist-info/WHEEL
stellar_core_prometheus_exporter-0.10.6.dist-info/entry_points.txt
stellar_core_prometheus_exporter-0.10.6.dist-info/top_level.txt
stellar_core_prometheus_exporter-0.10.6.dist-info/RECORD
