Metadata-Version: 2.1
Name: stellar-core-prometheus-exporter
Version: 0.10.6
Summary: Export stellar core metrics in prometheus format
Home-page: https://github.com/stellar/stellar-core-prometheus-exporter
Author: Stellar Development Foundation
Author-email: ops@stellar.org
License: Apache Software License 2.0
Keywords: prometheus,exporter,stellar
Platform: UNKNOWN
Classifier: Development Status :: 3 - Alpha
Classifier: Programming Language :: Python :: 2
Classifier: Programming Language :: Python :: 3
Classifier: Intended Audience :: Information Technology
Classifier: Topic :: System :: Monitoring
Classifier: License :: OSI Approved :: Apache Software License
Requires-Dist: requests
